MetaRagTool/Constants.py
MetaRagTool/__init__.py
MetaRagTool/Apps/GradioApps.py
MetaRagTool/Apps/__init__.py
MetaRagTool/Encoders/Encoder.py
MetaRagTool/Encoders/OtherEncoders.py
MetaRagTool/Encoders/Reranker.py
MetaRagTool/Encoders/SentenceTransformerEncoder.py
MetaRagTool/Encoders/__init__.py
MetaRagTool/Evaluations/Evals.py
MetaRagTool/Evaluations/TestManager.py
MetaRagTool/Evaluations/__init__.py
MetaRagTool/LLM/GoogleGemini.py
MetaRagTool/LLM/JudgeLLM.py
MetaRagTool/LLM/LLMIdentity.py
MetaRagTool/LLM/OpenaiGpt.py
MetaRagTool/LLM/__init__.py
MetaRagTool/RAG/Chunkers.py
MetaRagTool/RAG/DocumentStructs.py
MetaRagTool/RAG/MetaRAG.py
MetaRagTool/RAG/__init__.py
MetaRagTool/Utils/DataLoader.py
MetaRagTool/Utils/MRUtils.py
MetaRagTool/Utils/MetaRagConfig.py
MetaRagTool/Utils/__init__.py
metaragtool-0.3.41.dist-info/licenses/LICENSE.txt
metaragtool-0.3.41.dist-info/METADATA
metaragtool-0.3.41.dist-info/WHEEL
metaragtool-0.3.41.dist-info/top_level.txt
metaragtool-0.3.41.dist-info/RECORD
